Hubby/Hubby.py
Hubby/Private.py
Hubby/__init__.py
HubbyWrapper-1.0.0.dist-info/LICENSE
HubbyWrapper-1.0.0.dist-info/METADATA
HubbyWrapper-1.0.0.dist-info/WHEEL
HubbyWrapper-1.0.0.dist-info/top_level.txt
HubbyWrapper-1.0.0.dist-info/RECORD
