Metadata-Version: 2.1
Name: HubbyWrapper
Version: 1.0.0
Summary: Hubby, a Python library for interacting with the GitHub API
Author-email: Webbrowser11 <terpstragraham@gmail.com>, w_h_at <whatonscratch@gmail.com>
License: BSD-3-Clause
Keywords: GitHub,API,Python,Hubby
Classifier: Programming Language :: Python :: 3
Classifier: License :: OSI Approved :: BSD License
Classifier: Operating System :: OS Independent
Requires-Python: >=3.12
License-File: LICENSE
